qlispc/__init__.py
qlispc/assembly.cpython-310-x86_64-linux-gnu.so
qlispc/assembly.pyi
qlispc/base.py
qlispc/base.pyi
qlispc/commands.py
qlispc/commands.pyi
qlispc/compiler.cpython-310-x86_64-linux-gnu.so
qlispc/compiler.pyi
qlispc/config.py
qlispc/kernel_utils.py
qlispc/kernel_utils.pyi
qlispc/library.py
qlispc/library.pyi
qlispc/macro.cpython-310-x86_64-linux-gnu.so
qlispc/macro.pyi
qlispc/namespace.py
qlispc/optimize.py
qlispc/prog.py
qlispc/prog.pyi
qlispc/utils.cpython-310-x86_64-linux-gnu.so
qlispc/utils.pyi
qlispc/version.py
qlispc/vm.cpython-310-x86_64-linux-gnu.so
qlispc/vm.pyi
qlispc/arch/__init__.py
qlispc/arch/general.py
qlispc/arch/baqis/__init__.py
qlispc/arch/baqis/code.py
qlispc/arch/baqis/config.py
qlispc/arch/baqis/data.py
qlispc/libs/AshN.py
qlispc/libs/__init__.py
qlispc/libs/kak.py
qlispc/libs/measure.py
qlispc/libs/pi2.py
qlispc/libs/readout.py
qlispc/libs/stdlib.py
qlispc/libs/toffoli.py
qlispc/libs/u3.py
qlispc/stdlib/__init__.py
qlispc/tools/__init__.py
qlispc/tools/dicttree.py
qlispc/tools/geo.py
qlispc/tools/scan.py
qlispc2/__init__.py
qlispc2/interpreter.py
qlispc2/parse.py
qlispc2/tokenize.py
qlispc2/compiler/__init__.py
qlispc2/compiler/instructions.py
qlispc2/compiler/library.py
qlispc2/compiler/opcode.py
qlispc2/compiler/precompler.py
qlispc2/compiler/qcompiler.py
qlispc2/compiler/stackvm.py
qlispc2/compiler/vm.py
qlispc2/compiler/libs/__init__.py
qlispc2/compiler/libs/cz_base.py
qlispc2/compiler/libs/pmw2.py
qlispc2/compiler/libs/pmw4.py
qlispc2/compiler/libs/std.py
qlispc2/compiler/libs/u3.py
qlispc-1.2.2.dist-info/METADATA
qlispc-1.2.2.dist-info/WHEEL
qlispc-1.2.2.dist-info/top_level.txt
qlispc-1.2.2.dist-info/RECORD
qlispc-1.2.2.dist-info/licenses/LICENSE
