Metadata-Version: 2.4
Name: qlispc
Version: 1.2.2
Summary: Written quantum circuit int qlisp
Author-email: feihoo87 <feihoo87@gmail.com>
Maintainer-email: feihoo87 <feihoo87@gmail.com>
Project-URL: Homepage, https://systemq.baqis.ac.cn
Keywords: qlisp,quantum,quantum computing,quantum programming,quantum circuit
Classifier: Development Status :: 3 - Alpha
Classifier: Intended Audience :: Developers
Classifier: Intended Audience :: Science/Research
Classifier: Operating System :: Microsoft :: Windows
Classifier: Operating System :: POSIX :: Linux
Classifier: Operating System :: MacOS :: MacOS X
Classifier: Topic :: Scientific/Engineering
Classifier: Programming Language :: Python
Classifier: Programming Language :: Python :: 3.10
Classifier: Programming Language :: Python :: 3.11
Requires-Python: >=3.10
License-File: LICENSE
Requires-Dist: dill>=0.3.6
Requires-Dist: numpy>=1.13.3
Requires-Dist: ply>=3.11
Requires-Dist: pycycles>=1.0.8
Requires-Dist: qlisp>=1.1.4
Requires-Dist: qlispreg>=0.0.1
Requires-Dist: scipy>=1.0.0
Requires-Dist: waveforms>=1.8.9
Dynamic: license-file
